.VERSION
AUTHORS.rst
CONTRIBUTING.rst
HISTORY.rst
LICENSE
MANIFEST.in
Pipfile
Pipfile.lock
README.rst
USAGE.rst
dev-requirements.txt
requirements.txt
setup.cfg
setup.py
docs/Makefile
docs/authors.rst
docs/conf.py
docs/contributing.rst
docs/history.rst
docs/index.rst
docs/installation.rst
docs/readme.rst
docs/usage.rst
powermolegui/.DS_Store
powermolegui/.VERSION
powermolegui/AUTHORS.rst
powermolegui/CONTRIBUTING.rst
powermolegui/HISTORY.rst
powermolegui/LICENSE
powermolegui/Pipfile
powermolegui/Pipfile.lock
powermolegui/README.rst
powermolegui/USAGE.rst
powermolegui/__init__.py
powermolegui/_version.py
powermolegui/dev-requirements.txt
powermolegui/powermolegui.py
powermolegui/powermoleguiexceptions.py
powermolegui/requirements.txt
powermolegui.egg-info/PKG-INFO
powermolegui.egg-info/SOURCES.txt
powermolegui.egg-info/dependency_links.txt
powermolegui.egg-info/entry_points.txt
powermolegui.egg-info/not-zip-safe
powermolegui.egg-info/requires.txt
powermolegui.egg-info/top_level.txt
powermolegui/__pycache__/__init__.cpython-310.pyc
powermolegui/__pycache__/_version.cpython-310.pyc
powermolegui/__pycache__/powermolegui.cpython-310.pyc
powermolegui/__pycache__/powermoleguiexceptions.cpython-310.pyc
powermolegui/conf/logging.json-example
powermolegui/icon/application_icon_tunnel.png
powermolegui/lib/__init__.py
powermolegui/lib/animation.py
powermolegui/lib/application.py
powermolegui/lib/frames.py
powermolegui/lib/helpers.py
powermolegui/lib/items.py
powermolegui/lib/logging.py
powermolegui/lib/windows.py
powermolegui/lib/__pycache__/__init__.cpython-310.pyc
powermolegui/lib/__pycache__/animation.cpython-310.pyc
powermolegui/lib/__pycache__/application.cpython-310.pyc
powermolegui/lib/__pycache__/frames.cpython-310.pyc
powermolegui/lib/__pycache__/helpers.cpython-310.pyc
powermolegui/lib/__pycache__/items.cpython-310.pyc
powermolegui/lib/__pycache__/logging.cpython-310.pyc
powermolegui/lib/__pycache__/windows.cpython-310.pyc
powermolegui/settings/.gitignore
tests/test_powermolegui.py