Metadata-Version: 2.1
Name: powermolegui
Version: 0.2.17
Summary: powermole(gui) allows you to connect to a target destination host via one or more intermediaries, offering a variety of modes (FOR and TOR) and options (TRANSFER and COMMAND) to perform a variety of tasks
Home-page: https://github.com/yutanicorp/powermolegui
Author: Vincent Schouten
Author-email: powermole@protonmail.com
License: MIT
Keywords: powermole powermolegui ssh proxyjump forwarding tor gui security
Classifier: Development Status :: 4 - Beta
Classifier: Intended Audience :: Developers
Classifier: License :: OSI Approved :: MIT License
Classifier: Natural Language :: English
Classifier: Programming Language :: Python :: 3.7
Classifier: Topic :: System :: Networking
Classifier: Topic :: Security
Classifier: Topic :: Internet
Classifier: Operating System :: MacOS
Classifier: Operating System :: POSIX
License-File: LICENSE
License-File: AUTHORS.rst
Requires-Dist: coloredlogs>=15.0.1
Requires-Dist: voluptuous~=0.11.7
Requires-Dist: powermolelib~=3.4.8
